<episodes>
<episode name = "Episode 24 - The Man Named Kasumi Kenshiro"></episode>
<episode name = "Episode 23 - Erika Arendt, the Lone Girl"></episode>
<episode name = "Episode 22 - Life of the Successor"></episode>
<episode name = "Episode 21 - Destined to Die Together"></episode>
<episode name = "Episode 20 - The Path of Kasumi Kenshin"></episode>
<episode name = "Episode 19 - Men Who Scatter and Die"></episode>
<episode name = "Episode 18 - The Setting Sun of the Nahash People"></episode>
<episode name = "Episode 17 - Thoughts That Never Cross"></episode>
<episode name = "Episode 16 - Migadol&apos;s Thunderbolts"></episode>
<episode name = "Episode 15 - The Prophecy That Came True"></episode>
<episode name = "Episode 14 - Admiration for a Brother"></episode>
<episode name = "Episode 13 - God&apos;s Chosen People"></episode>
<episode name = "Episode 12 - Fists for Pengyou"></episode>
<episode name = "Episode 11 - Heaven Dipper Sacred Yin Fist"></episode>
<episode name = "Episode 10 - The Young Successor"></episode>
<episode name = "Episode 9 - Forgiver"></episode>
<episode name = "Episode 8 - Battle of Destiny"></episode>
<episode name = "Episode 7 - Two Thousand Year Love"></episode>
<episode name = "Episode 6 - Departing Swallow"></episode>
<episode name = "Episode 5 - Grudge of the Hungry Wolf"></episode>
<episode name = "Episode 4 - Origin of the Divine Fist of the North Star"></episode>
<episode name = "Episode 3 - Bloodstained Death Bird Demon"></episode>
<episode name = "Episode 2 - Unattainable Desires"></episode>
<episode name = "Episode 1 - Successor to the Divine Fist of the North Star: Kasumi Kenshiro"></episode>
</episodes>