<episodes>
<episode name = "Episode 12 - Last Period"></episode>
<episode name = "Episode 11 - Fictional Story"></episode>
<episode name = "Episode 10 - The Happy Elements Episode"></episode>
<episode name = "Episode 9 - Expanding Galaxy"></episode>
<episode name = "Episode 8 - Swimsuit Episode"></episode>
<episode name = "Episode 7 - Animal Friends"></episode>
<episode name = "Episode 6 - Confessions of a Mask"></episode>
<episode name = "Episode 5 - The Swamp&apos;s Name"></episode>
<episode name = "Episode 4 - Rich in Zel"></episode>
<episode name = "Episode 3 - Hand-To-Mouth-Life"></episode>
<episode name = "Episode 2 - Hot Springs Custom"></episode>
<episode name = "Episode 1 - Notice of Completion"></episode>
</episodes>