<episodes>
<episode name = "Episode 49 - The Final Victor"></episode>
<episode name = "Episode 48 - Takeoff into Confusion"></episode>
<episode name = "Episode 47 - Collision in Space"></episode>
<episode name = "Episode 46 - Milliardo\u2019s Decision"></episode>
<episode name = "Episode 45 - Signs of the Final Battle"></episode>
<episode name = "Episode 44 - Go Forth, Gundam Team"></episode>
<episode name = "Episode 43 - Target: Earth"></episode>
<episode name = "Episode 42 - Battleship Libra"></episode>
<episode name = "Episode 41 - Crossfire at Barge"></episode>
<episode name = "Episode 40 - A New Leader"></episode>
<episode name = "Episode 39 - Trowa\u2019s Return to the Battlefield"></episode>
<episode name = "Episode 38 - The Birth of Queen Relena"></episode>
<episode name = "Episode 37 - Zero vs. Epyon"></episode>
<episode name = "Episode 36 - Sanc Kingdom\u2019s Collapse"></episode>
<episode name = "Episode 35 - The Return of Wu Fei"></episode>
<episode name = "Episode 34 - And It\u2019s Name is Epyon"></episode>
<episode name = "Episode 33 - The Lonely Battlefield"></episode>
<episode name = "Episode 32 - The God of Death Meets Zero"></episode>
<episode name = "Episode 31 - The Glass Kingdom"></episode>
<episode name = "Episode 30 - The Reunion With Relena"></episode>
<episode name = "Episode 29 - The Heroine of the Battlefield"></episode>
<episode name = "Episode 28 - Passing Destinies"></episode>
<episode name = "Episode 27 - The Locus of Victory and Defeat"></episode>
<episode name = "Episode 26 - The Eternal Flame of the Shooting Stars"></episode>
<episode name = "Episode 25 - Quatre vs. Heero"></episode>
<episode name = "Episode 24 - The Gundam They Called Zero"></episode>
<episode name = "Episode 23 - Duo, God of Death Once Again"></episode>
<episode name = "Episode 22 - The Fight for Independence"></episode>
<episode name = "Episode 21 - Grief Stricken Quatre"></episode>
<episode name = "Episode 20 - The Lunar Base Infiltration"></episode>
<episode name = "Episode 19 - Assault on Barge"></episode>
<episode name = "Episode 18 - Tallgeese Destroyed"></episode>
<episode name = "Episode 17 - Betrayed by Home, Far Away"></episode>
<episode name = "Episode 16 - The Sorrowful Battle"></episode>
<episode name = "Episode 15 - To the Battleground, Antarctica"></episode>
<episode name = "Episode 14 - The Order to Destroy 01"></episode>
<episode name = "Episode 13 - Catherine\u2019s Tears"></episode>
<episode name = "Episode 12 - Bewildered Warriors"></episode>
<episode name = "Episode 11 - The Whereabouts of Happiness"></episode>
<episode name = "Episode 10 - Heero, Distracted by Defeat"></episode>
<episode name = "Episode 9 - Portrait of a Ruined Country"></episode>
<episode name = "Episode 8 - The Treize Assassination"></episode>
<episode name = "Episode 7 - Scenario for Bloodshed"></episode>
<episode name = "Episode 6 - Party Night"></episode>
<episode name = "Episode 5 - Relena\u2019s Secret"></episode>
<episode name = "Episode 4 - The Victoria Nightmare"></episode>
<episode name = "Episode 3 - 5 Gundams Confirmed"></episode>
<episode name = "Episode 2 - The Gundam Deathscythe"></episode>
<episode name = "Episode 1 - The Shooting Star She Saw"></episode>
</episodes>