<episodes>
<episode name = "Episode 12 - Tanzanite of Rebirth"></episode>
<episode name = "Episode 11 - Peridot of Blessings"></episode>
<episode name = "Episode 10 - The Lapis Lazuli of Guidance"></episode>
<episode name = "Episode 9 - The Alexandrite&apos;s Secret"></episode>
<episode name = "Episode 8 - The Angel&apos;s Aquamarine"></episode>
<episode name = "Episode 7 - The Jade of Succession"></episode>
<episode name = "Episode 6 - Perilous Turquoise"></episode>
<episode name = "Episode 5 - Opal of Encounters"></episode>
<episode name = "Episode 4 - The Fighting Garnet"></episode>
<episode name = "Episode 3 - Insight of the Cat&apos;s Eye"></episode>
<episode name = "Episode 2 - The Ruby&apos;s Truth"></episode>
<episode name = "Episode 1 - Seigi of the Pink Sapphire"></episode>
</episodes>