<episodes>
<episode name = "Episode 12 - Today&apos;s Main Race! The Gilded Vessel Obstacle Course (G1)"></episode>
<episode name = "Episode 11 - Umayon Suspense Theater"></episode>
<episode name = "Episode 10 - You Get Spooked, You Lose! Test of Courage Showdown!"></episode>
<episode name = "Episode 9 - Make the Dream Come True! Getaway Sisters"></episode>
<episode name = "Episode 8 - Hero Theater: Uma Soldier V!!"></episode>
<episode name = "Episode 7 - Time to Hunt Rhinoceros Beetles! BNW"></episode>
<episode name = "Episode 6 - An Elegant Lunch for Elegant Young Ladies"></episode>
<episode name = "Episode 5 - A Major Clash?! The Ramen Cup (GII)"></episode>
<episode name = "Episode 4 - The Opera: &quot;Alas, It Is My Fate&quot;"></episode>
<episode name = "Episode 3 - The World You&apos;ve Dreamed of Is Right in Front of You"></episode>
<episode name = "Episode 2 - Newly Filmed! The Tracen Academy Video Introduction"></episode>
<episode name = "Episode 1 - 40% And Below! Tracen Academy Special Make-up Exams"></episode>
</episodes>